CHANGES.txt
CONTRIBUTORS.txt
COPYRIGHT.txt
LICENSE.txt
MANIFEST.in
README.rst
example.cfg
setup.cfg
setup.py
src/z3c/__init__.py
src/z3c.recipe.staticlxml.egg-info/PKG-INFO
src/z3c.recipe.staticlxml.egg-info/SOURCES.txt
src/z3c.recipe.staticlxml.egg-info/dependency_links.txt
src/z3c.recipe.staticlxml.egg-info/entry_points.txt
src/z3c.recipe.staticlxml.egg-info/namespace_packages.txt
src/z3c.recipe.staticlxml.egg-info/not-zip-safe
src/z3c.recipe.staticlxml.egg-info/requires.txt
src/z3c.recipe.staticlxml.egg-info/top_level.txt
src/z3c/recipe/__init__.py
src/z3c/recipe/staticlxml/README.txt
src/z3c/recipe/staticlxml/__init__.py
src/z3c/recipe/staticlxml/tests/__init__.py
src/z3c/recipe/staticlxml/tests/test_docs.py