Metadata-Version: 1.1
Name: z3c.recipe.staticlxml
Version: 0.9
Summary: A recipe to build lxml
Home-page: http://svn.zope.org/z3c.recipe.staticlxml/trunk
Author: Stefan Eletzhofer
Author-email: se@nexiles.de
License: ZPL
Keywords: buildout recipe lxml static
Platform: UNKNOWN
Classifier: Framework :: Buildout
Classifier: Intended Audience :: Developers
Classifier: Topic :: Software Development :: Build Tools
Classifier: Topic :: Software Development :: Libraries :: Python Modules
Classifier: License :: OSI Approved :: Zope Public License
